block/datasets/__init__.py
block/datasets/factory.py
block/datasets/tdiuc.py
block/datasets/vg.py
block/datasets/vqa2.py
block/datasets/vqa2vg.py
block/datasets/vqa_utils.py
block/datasets/vrd.py
block/models/__init__.py
block/models/criterions/__init__.py
block/models/criterions/factory.py
block/models/criterions/kl_divergence.py
block/models/criterions/vqa_cross_entropy.py
block/models/criterions/vrd_bce.py
block/models/metrics/__init__.py
block/models/metrics/compute_oe_accuracy.py
block/models/metrics/factory.py
block/models/metrics/vqa_accuracies.py
block/models/metrics/vqa_accuracy.py
block/models/metrics/vrd_predicate.py
block/models/metrics/vrd_rel_phrase.py
block/models/metrics/vrd_utils.py
block/models/networks/__init__.py
block/models/networks/factory.py
block/models/networks/mlp.py
block/models/networks/vqa_net.py
block/models/networks/vrd_net.py
block/models/networks/fusions/__init__.py
block/models/networks/fusions/compactbilinearpooling.py
block/models/networks/fusions/factory.py
block/models/networks/fusions/fusions.py
block/optimizers/__init__.py
block/optimizers/factory.py
block/optimizers/lr_scheduler.py
bootstrap/datasets/__init__.py
bootstrap/datasets/dataset.py
bootstrap/datasets/factory.py
bootstrap/datasets/transforms.py
bootstrap/datasets/utils.py
bootstrap/engines/__init__.py
bootstrap/engines/engine.py
bootstrap/engines/factory.py
bootstrap/engines/logger.py
bootstrap/lib/__init__.py
bootstrap/lib/logger.py
bootstrap/lib/options.py
bootstrap/lib/overwrite_print.py
bootstrap/lib/utils.py
bootstrap/models/__init__.py
bootstrap/models/factory.py
bootstrap/models/model.py
bootstrap/models/criterions/__init__.py
bootstrap/models/criterions/bce.py
bootstrap/models/criterions/cross_entropy.py
bootstrap/models/criterions/factory.py
bootstrap/models/criterions/nll.py
bootstrap/models/metrics/__init__.py
bootstrap/models/metrics/accuracy.py
bootstrap/models/metrics/factory.py
murel.bootstrap.pytorch-0.0.0.dist-info/DESCRIPTION.rst
murel.bootstrap.pytorch-0.0.0.dist-info/METADATA
murel.bootstrap.pytorch-0.0.0.dist-info/RECORD
murel.bootstrap.pytorch-0.0.0.dist-info/WHEEL
murel.bootstrap.pytorch-0.0.0.dist-info/metadata.json
murel.bootstrap.pytorch-0.0.0.dist-info/top_level.txt
