Metadata-Version: 2.0
Name: murel.bootstrap.pytorch
Version: 0.0.0
Summary: MUREL: Multimodal Relational Reasoning for Visual Question Answering
Home-page: https://github.com/cadene/murel.bootstrap.pytorch
Author: Remi Cadene
Author-email: remi.cadene@icloud.com
License: UNKNOWN
Keywords: pytorch murel block vqa tdiuc visual question answering visual relationship detection relation bootstrap deep learning aaai cvpr
Platform: UNKNOWN
Classifier: Development Status :: 3 - Alpha
Classifier: Intended Audience :: Developers
Classifier: Topic :: Software Development :: Build Tools
Classifier: License :: OSI Approved :: MIT License
Classifier: Programming Language :: Python :: 3.7
Requires-Dist: bootstrap.pytorch
Requires-Dist: skipthoughts
Requires-Dist: pretrainedmodels
Requires-Dist: opencv-python
Requires-Dist: block.bootstrap.pytorch
Provides-Extra: test
Requires-Dist: pytest; extra == 'test'
